LICENSE
MANIFEST.in
README.md
setup.py
django_token/__init__.py
django_token/admin.py
django_token/backends.py
django_token/middleware.py
django_token/models.py
django_token/tests.py
django_token/views.py
django_token.egg-info/PKG-INFO
django_token.egg-info/SOURCES.txt
django_token.egg-info/dependency_links.txt
django_token.egg-info/requires.txt
django_token.egg-info/top_level.txt
django_token/management/__init__.py
django_token/management/commands/__init__.py
django_token/management/commands/reset_tokens.py
django_token/migrations/0001_initial.py
django_token/migrations/__init__.py