Metadata-Version: 1.0
Name: django-token
Version: 0.1.2
Summary: Simple token based authentication for Django
Home-page: https://github.com/jasonbeverage/django-token
Author: Jason Beverage
Author-email: UNKNOWN
License: UNKNOWN
Platform: UNKNOWN
